predica/__init__.py
predica/predicates.py
predica-0.1.1.dist-info/METADATA
predica-0.1.1.dist-info/WHEEL
predica-0.1.1.dist-info/licenses/LICENSE
predica-0.1.1.dist-info/RECORD
