Metadata-Version: 2.1
Name: predica
Version: 0.1.1
Summary: Predicates for use in higher-order functions.
Project-URL: Repository, https://github.com/y-src/predica
Project-URL: Issues, https://github.com/y-src/predica/issues
Author: Rahul Yadav
License: MIT License
License-File: LICENSE
Keywords: composition,fp,functional programming,predicates,type-safety
Classifier: Development Status :: 4 - Beta
Classifier: Intended Audience :: Developers
Classifier: License :: OSI Approved :: MIT License
Classifier: Operating System :: OS Independent
Classifier: Programming Language :: Python :: 3
Classifier: Topic :: Software Development :: Libraries :: Python Modules
Classifier: Topic :: Utilities
Classifier: Typing :: Typed
Requires-Python: >=3.8
